{
	"format_version": "1.8.0",
	"animations": {
		"idle": {
			"loop": true,
			"animation_length": 3,
			"bones": {
				"main": {
					"rotation": {
						"0.0": {
							"vector": [0, 0, 0]
						},
						"1.5": {
							"vector": [0, 0, 0]
						},
						"3.0": {
							"vector": [0, 0, 0]
						}
					},
					"position": {
						"0.0": {
							"vector": [0, 0, 0]
						},
						"1.5": {
							"vector": [0, -0.3, 0]
						},
						"3.0": {
							"vector": [0, 0, 0]
						}
					}
				},
				"body": {
					"rotation": {
						"0.0": {
							"vector": [0, 0, 0]
						},
						"1.5": {
							"vector": [-6, 0, 0]
						},
						"3.0": {
							"vector": [0, 0, 0]
						}
					},
					"position": {
						"0.0": {
							"vector": [0, 0, 0]
						},
						"1.5": {
							"vector": [0, -0.3, 0]
						},
						"3.0": {
							"vector": [0, 0, 0]
						}
					}
				},
				"body_bac": {
					"rotation": {
						"0.0": {
							"vector": [0, 0, 0]
						},
						"1.5": {
							"vector": [11, 0, 0]
						},
						"3.0": {
							"vector": [0, 0, 0]
						}
					},
					"position": {
						"0.0": {
							"vector": [0, 0, 0]
						},
						"1.5": {
							"vector": [0, 0.1, 0]
						},
						"3.0": {
							"vector": [0, 0, 0]
						}
					},
					"scale": {
						"0.0": {
							"vector": [1.05, 1.05, 1.05]
						},
						"1.5": {
							"vector": [1, 1, 1]
						},
						"3.0": {
							"vector": [1.05, 1.05, 1.05]
						}
					}
				},
				"mainhead": {
					"rotation": {
						"0.0": {
							"vector": [0, 0, 0]
						},
						"1.5": {
							"vector": [11, 0, 0]
						},
						"3.0": {
							"vector": [0, 0, 0]
						}
					},
					"position": {
						"0.0": {
							"vector": [0, 0, 0]
						},
						"1.5": {
							"vector": [0, 0.1, 0]
						},
						"3.0": {
							"vector": [0, 0, 0]
						}
					}
				}
			}
		},
		"walk": {
			"loop": true,
			"animation_length": 1,
			"bones": {
				"main": {
					"rotation": {
						"0.0": {
							"vector": [0, 1, 0]
						},
						"0.25": {
							"vector": [0, -1, 0]
						},
						"0.5": {
							"vector": [0, 1, 0]
						},
						"0.75": {
							"vector": [0, -1, 0]
						},
						"1.0": {
							"vector": [0, 1, 0]
						}
					},
					"position": {
						"0.0": {
							"vector": [0, 0, 0]
						},
						"0.25": {
							"vector": [0, -0.2, 0]
						},
						"0.5": {
							"vector": [0, 0, 0]
						},
						"0.75": {
							"vector": [0, -0.2, 0]
						},
						"1.0": {
							"vector": [0, 0, 0]
						}
					}
				},
				"body": {
					"rotation": {
						"0.0": {
							"vector": [0, 0, 0]
						},
						"0.25": {
							"vector": [0, 0, 0]
						},
						"0.5": {
							"vector": [0, 0, 0]
						},
						"0.75": {
							"vector": [0, 0, 0]
						},
						"1.0": {
							"vector": [0, 0, 0]
						}
					},
					"position": {
						"0.0": {
							"vector": [0, 0, 0]
						},
						"0.25": {
							"vector": [0, -0.6, 0]
						},
						"0.5": {
							"vector": [0, 0.2, 0]
						},
						"0.75": {
							"vector": [0, -0.6, 0]
						},
						"1.0": {
							"vector": [0, -0.1, 0]
						}
					}
				},
				"body_bac": {
					"rotation": {
						"0.0": {
							"vector": [0, -7, 0]
						},
						"0.25": {
							"vector": [0, 7, 0]
						},
						"0.5": {
							"vector": [0, -7, 0]
						},
						"0.75": {
							"vector": [0, 7, 0]
						},
						"1.0": {
							"vector": [0, -7, 0]
						}
					},
					"position": {
						"0.0": {
							"vector": [0, 0, 0]
						},
						"0.25": {
							"vector": [0, 0, 0]
						},
						"0.5": {
							"vector": [0, 0, 0]
						},
						"0.75": {
							"vector": [0, 0, 0]
						},
						"1.0": {
							"vector": [0, 0, 0]
						}
					},
					"scale": {
						"0.0": {
							"vector": [1, 1, 1]
						},
						"0.25": {
							"vector": [1.05, 1.05, 1.05]
						},
						"0.5": {
							"vector": [1, 1, 1]
						},
						"0.75": {
							"vector": [1.05, 1.05, 1.05]
						},
						"1.0": {
							"vector": [1, 1, 1]
						}
					}
				},
				"mainhead": {
					"rotation": {
						"0.0": {
							"vector": [0, 5, 0]
						},
						"0.25": {
							"vector": [-2, -5, 0]
						},
						"0.5": {
							"vector": [0, 5, 0]
						},
						"0.75": {
							"vector": [-2, -5, 0]
						},
						"1.0": {
							"vector": [0, 5, 0]
						}
					},
					"position": {
						"0.0": {
							"vector": [0, 0, 0]
						},
						"0.25": {
							"vector": [0, 0, 0]
						},
						"0.5": {
							"vector": [0, 0, 0]
						},
						"0.75": {
							"vector": [0, 0, 0]
						},
						"1.0": {
							"vector": [0, 0, 0]
						}
					}
				},
				"left_leg1": {
					"rotation": {
						"0.0": {
							"vector": [0, 20, 0]
						},
						"0.25": {
							"vector": [0, -20, 0]
						},
						"0.5": {
							"vector": [0, 20, 0]
						},
						"0.75": {
							"vector": [0, -20, 0]
						},
						"1.0": {
							"vector": [0, 20, 0]
						}
					},
					"position": {
						"0.0": {
							"vector": [0, 0, 0]
						},
						"0.25": {
							"vector": [0, 0, 0]
						},
						"0.5": {
							"vector": [0, 0, 0]
						},
						"0.75": {
							"vector": [0, 0, 0]
						},
						"1.0": {
							"vector": [0, 0, 0]
						}
					}
				},
				"left_leg2": {
					"rotation": {
						"0.0": {
							"vector": [0, -21, 0]
						},
						"0.25": {
							"vector": [0, 41, 0]
						},
						"0.5": {
							"vector": [0, -21, 0]
						},
						"0.75": {
							"vector": [0, 41, 0]
						},
						"1.0": {
							"vector": [0, -21, 0]
						}
					},
					"position": {
						"0.0": {
							"vector": [0, 0, 0]
						},
						"0.25": {
							"vector": [0, 0, 0]
						},
						"0.5": {
							"vector": [0, 0, 0]
						},
						"0.75": {
							"vector": [0, 0, 0]
						},
						"1.0": {
							"vector": [0, 0, 0]
						}
					}
				},
				"left_leg3": {
					"rotation": {
						"0.0": {
							"vector": [-6.99322, 34.01096, 0.36279]
						},
						"0.25": {
							"vector": [-8.59185, -10.88081, 3.94237]
						},
						"0.5": {
							"vector": [-6.99322, 34.01096, 0.36279]
						},
						"0.75": {
							"vector": [-8.59185, -10.88081, 3.94237]
						},
						"1.0": {
							"vector": [-6.99322, 34.01096, 0.36279]
						}
					},
					"position": {
						"0.0": {
							"vector": [0, 0, 0]
						},
						"0.25": {
							"vector": [0, 0, 0]
						},
						"0.5": {
							"vector": [0, 0, 0]
						},
						"0.75": {
							"vector": [0, 0, 0]
						},
						"1.0": {
							"vector": [0, 0, 0]
						}
					}
				},
				"right_leg1": {
					"rotation": {
						"0.0": {
							"vector": [0, -4, 0]
						},
						"0.25": {
							"vector": [11.14743, 49.68391, 5.01926]
						},
						"0.5": {
							"vector": [0, -4, 0]
						},
						"0.75": {
							"vector": [11.14743, 49.68391, 5.01926]
						},
						"1.0": {
							"vector": [0, -4, 0]
						}
					},
					"position": {
						"0.0": {
							"vector": [0, 0, 0]
						},
						"0.25": {
							"vector": [0, 0, 0]
						},
						"0.5": {
							"vector": [0, 0, 0]
						},
						"0.75": {
							"vector": [0, 0, 0]
						},
						"1.0": {
							"vector": [0, 0, 0]
						}
					}
				},
				"right_leg2": {
					"rotation": {
						"0.0": {
							"vector": [0, -17, 0]
						},
						"0.25": {
							"vector": [0, -54, 0]
						},
						"0.5": {
							"vector": [0, -17, 0]
						},
						"0.75": {
							"vector": [0, -54, 0]
						},
						"1.0": {
							"vector": [0, -17, 0]
						}
					},
					"position": {
						"0.0": {
							"vector": [0, 0, 0]
						},
						"0.25": {
							"vector": [0, 0, 0]
						},
						"0.5": {
							"vector": [0, 0, 0]
						},
						"0.75": {
							"vector": [0, 0, 0]
						},
						"1.0": {
							"vector": [0, 0, 0]
						}
					}
				},
				"right_leg3": {
					"rotation": {
						"0.0": {
							"vector": [-10.38397, 13.77309, -5.86755]
						},
						"0.25": {
							"vector": [-7.06383, -51.8027, 3.16459]
						},
						"0.5": {
							"vector": [-10.38397, 13.77309, -5.86755]
						},
						"0.75": {
							"vector": [-7.06383, -51.8027, 3.16459]
						},
						"1.0": {
							"vector": [-10.38397, 13.77309, -5.86755]
						}
					},
					"position": {
						"0.0": {
							"vector": [0, 0, 0]
						},
						"0.25": {
							"vector": [0, 0, 0]
						},
						"0.5": {
							"vector": [0, 0, 0]
						},
						"0.75": {
							"vector": [0, 0, 0]
						},
						"1.0": {
							"vector": [0, 0, 0]
						}
					}
				}
			}
		},
		"attack": {
			"animation_length": 1,
			"bones": {
				"body": {
					"rotation": {
						"0.0": {
							"vector": [-11, 0, 0]
						},
						"0.1667": {
							"vector": [0, 0, 0]
						},
						"0.4167": {
							"vector": [0, 0, 0]
						},
						"0.5": {
							"vector": [-11, 0, 0]
						},
						"0.75": {
							"vector": [0, 0, 0]
						}
					}
				},
				"mainhead": {
					"rotation": {
						"0.0": {
							"vector": [-17, 0, 0]
						},
						"0.1667": {
							"vector": [0, 0, 0]
						},
						"0.4167": {
							"vector": [0, 0, 0]
						},
						"0.5": {
							"vector": [-17, 0, 0]
						},
						"0.75": {
							"vector": [0, 0, 0]
						}
					}
				}
			}
		},
		"death": {
			"loop": "hold_on_last_frame",
			"animation_length": 1,
			"bones": {
				"main": {
					"rotation": {
						"0.0": {
							"vector": [0, 0, 0]
						},
						"0.125": {
							"vector": [-111, 0, 0]
						},
						"0.25": {
							"vector": [-146.03642, -1.67705, 2.48782]
						},
						"0.375": {
							"vector": [-146.40545, -5.57236, 8.31669]
						},
						"0.5417": {
							"vector": [-152.64599, -10.87476, 16.87939]
						},
						"0.6667": {
							"vector": [-152.64599, -10.87476, 16.87939]
						},
						"0.7917": {
							"vector": [-152.82044, -11.33291, 17.78523]
						}
					},
					"position": {
						"0.0": {
							"vector": [0, 0, 0]
						},
						"0.125": {
							"vector": [0, 5.1, 0]
						},
						"0.25": {
							"vector": [0, 0.4, 1.6]
						},
						"0.375": {
							"vector": [0, -1.3, 1.6]
						},
						"0.5417": {
							"vector": [0, -1.3, 1.6]
						},
						"0.6667": {
							"vector": [0, -1.3, 1.6]
						},
						"0.7917": {
							"vector": [0, -1.5, 1.6]
						}
					}
				},
				"body": {
					"rotation": {
						"0.0": {
							"vector": [0, 0, 0]
						},
						"0.125": {
							"vector": [-5, 0, 0]
						},
						"0.25": {
							"vector": [-5, 0, 0]
						},
						"0.375": {
							"vector": [-5, 0, 0]
						},
						"0.5417": {
							"vector": [-8, 0, 0]
						},
						"0.6667": {
							"vector": [-8, 0, 0]
						},
						"0.7917": {
							"vector": [-8, 0, 0]
						}
					},
					"position": {
						"0.0": {
							"vector": [0, 0, 0]
						},
						"0.125": {
							"vector": [0, 0, 0]
						},
						"0.25": {
							"vector": [0, 0, 0]
						},
						"0.375": {
							"vector": [0, 0, 0]
						},
						"0.5417": {
							"vector": [0, 0, 0]
						},
						"0.6667": {
							"vector": [0, 0, 0]
						},
						"0.7917": {
							"vector": [0, 0, 0]
						}
					}
				},
				"body_bac": {
					"rotation": {
						"0.0": {
							"vector": [0, 0, 0]
						},
						"0.125": {
							"vector": [-46, 0, 0]
						},
						"0.25": {
							"vector": [-54, 0, 0]
						},
						"0.375": {
							"vector": [-41, 0, 0]
						},
						"0.5417": {
							"vector": [-59, 0, 0]
						},
						"0.6667": {
							"vector": [-49, 0, 0]
						},
						"0.7917": {
							"vector": [-59, 0, 0]
						}
					},
					"position": {
						"0.0": {
							"vector": [0, 0, 0]
						},
						"0.125": {
							"vector": [0, 0, 0]
						},
						"0.25": {
							"vector": [0, 0, 0]
						},
						"0.375": {
							"vector": [0, 0, 0]
						},
						"0.5417": {
							"vector": [0, 0, 0]
						},
						"0.6667": {
							"vector": [0, 0, 0]
						},
						"0.7917": {
							"vector": [0, 0, 0]
						}
					}
				},
				"mainhead": {
					"rotation": {
						"0.0": {
							"vector": [0, 0, 0]
						},
						"0.125": {
							"vector": [17, 0, 0]
						},
						"0.25": {
							"vector": [24, 0, 0]
						},
						"0.375": {
							"vector": [1, 0, 0]
						},
						"0.5417": {
							"vector": [19, 0, 0]
						},
						"0.6667": {
							"vector": [8, 0, 0]
						},
						"0.7917": {
							"vector": [29, 0, 0]
						}
					},
					"position": {
						"0.0": {
							"vector": [0, 0, 0]
						},
						"0.125": {
							"vector": [0, 0, 0]
						},
						"0.25": {
							"vector": [0, 0, 0]
						},
						"0.375": {
							"vector": [0, 0, 0]
						},
						"0.5417": {
							"vector": [0, 0, 0]
						},
						"0.6667": {
							"vector": [0, 0, 0]
						},
						"0.7917": {
							"vector": [0, 0, 0]
						}
					}
				},
				"left_leg1": {
					"rotation": {
						"0.0": {
							"vector": [0, 0, 0]
						},
						"0.125": {
							"vector": [0, 0, 0]
						},
						"0.25": {
							"vector": [0, 0, 0]
						},
						"0.375": {
							"vector": [0, 0, -24]
						},
						"0.5417": {
							"vector": [0, 0, 52]
						},
						"0.6667": {
							"vector": [0, 0, 29]
						},
						"0.7917": {
							"vector": [0, 0, 52]
						}
					},
					"position": {
						"0.0": {
							"vector": [0, 0, 0]
						},
						"0.125": {
							"vector": [0, 0, 0]
						},
						"0.25": {
							"vector": [0, 0, 0]
						},
						"0.375": {
							"vector": [0, 0, 0]
						},
						"0.5417": {
							"vector": [-1.4, 0.9, 0]
						},
						"0.6667": {
							"vector": [-1.4, 0.9, 0]
						},
						"0.7917": {
							"vector": [-1.4, 0.9, 0]
						}
					}
				},
				"left_leg2": {
					"rotation": {
						"0.0": {
							"vector": [0, 0, 0]
						},
						"0.125": {
							"vector": [0, 0, 0]
						},
						"0.25": {
							"vector": [0, 0, 0]
						},
						"0.375": {
							"vector": [0, 0, -14]
						},
						"0.5417": {
							"vector": [0, 0, 46]
						},
						"0.6667": {
							"vector": [0, 0, 34]
						},
						"0.7917": {
							"vector": [0, 0, 46]
						}
					},
					"position": {
						"0.0": {
							"vector": [0, 0, 0]
						},
						"0.125": {
							"vector": [0, 0, 0]
						},
						"0.25": {
							"vector": [0, 0, 0]
						},
						"0.375": {
							"vector": [0, 0, 0]
						},
						"0.5417": {
							"vector": [0, 0, 0]
						},
						"0.6667": {
							"vector": [0, 0, 0]
						},
						"0.7917": {
							"vector": [0, 0, 0]
						}
					}
				},
				"left_leg3": {
					"rotation": {
						"0.0": {
							"vector": [0, 0, 0]
						},
						"0.125": {
							"vector": [-10.45404, 14.78713, 27.97851]
						},
						"0.25": {
							"vector": [-10.45404, 14.78713, 27.97851]
						},
						"0.375": {
							"vector": [-0.40266, 13.94195, 1.07646]
						},
						"0.5417": {
							"vector": [-18.02801, 18.93453, 50.86271]
						},
						"0.6667": {
							"vector": [-13.42808, 15.9597, 36.4318]
						},
						"0.7917": {
							"vector": [-18.02801, 18.93453, 50.86271]
						}
					},
					"position": {
						"0.0": {
							"vector": [0, 0, 0]
						},
						"0.125": {
							"vector": [0, 0, 0]
						},
						"0.25": {
							"vector": [0, 0, 0]
						},
						"0.375": {
							"vector": [0, 0, 0]
						},
						"0.5417": {
							"vector": [0, 0, 0]
						},
						"0.6667": {
							"vector": [0, 0, 0]
						},
						"0.7917": {
							"vector": [0, 0, 0]
						}
					}
				},
				"right_leg1": {
					"rotation": {
						"0.0": {
							"vector": [0, 0, 0]
						},
						"0.125": {
							"vector": [0, 0, 0]
						},
						"0.25": {
							"vector": [0, 0, 0]
						},
						"0.375": {
							"vector": [0, 0, 18]
						},
						"0.5417": {
							"vector": [0, 0, -35]
						},
						"0.6667": {
							"vector": [0, 0, -15]
						},
						"0.7917": {
							"vector": [0, 0, -35]
						}
					},
					"position": {
						"0.0": {
							"vector": [0, 0, 0]
						},
						"0.125": {
							"vector": [0, 0, 0]
						},
						"0.25": {
							"vector": [0, 0, 0]
						},
						"0.375": {
							"vector": [0, 0, 0]
						},
						"0.5417": {
							"vector": [1.1, 0, 0]
						},
						"0.6667": {
							"vector": [1.1, 0, 0]
						},
						"0.7917": {
							"vector": [1.1, 0, 0]
						}
					}
				},
				"right_leg2": {
					"rotation": {
						"0.0": {
							"vector": [0, 0, 0]
						},
						"0.125": {
							"vector": [0, 0, 0]
						},
						"0.25": {
							"vector": [0, 0, 0]
						},
						"0.375": {
							"vector": [0, 0, 23]
						},
						"0.5417": {
							"vector": [0, 0, -45]
						},
						"0.6667": {
							"vector": [0, 0, -27]
						},
						"0.7917": {
							"vector": [0, 0, -45]
						}
					},
					"position": {
						"0.0": {
							"vector": [0, 0, 0]
						},
						"0.125": {
							"vector": [0, 0, 0]
						},
						"0.25": {
							"vector": [0, 0, 0]
						},
						"0.375": {
							"vector": [0, 0, 0]
						},
						"0.5417": {
							"vector": [0, 0, 0]
						},
						"0.6667": {
							"vector": [0, 0, 0]
						},
						"0.7917": {
							"vector": [0, 0, 0]
						}
					}
				},
				"right_leg3": {
					"rotation": {
						"0.0": {
							"vector": [0, 0, 0]
						},
						"0.125": {
							"vector": [-8.84272, -15.36412, -24.61727]
						},
						"0.25": {
							"vector": [-8.84272, -15.36412, -24.61727]
						},
						"0.375": {
							"vector": [5.49315, -16.6509, 15.88377]
						},
						"0.5417": {
							"vector": [-16.63952, -19.10373, -48.60042]
						},
						"0.6667": {
							"vector": [-11.043, -16.0351, -30.97235]
						},
						"0.7917": {
							"vector": [-16.63952, -19.10373, -48.60042]
						}
					},
					"position": {
						"0.0": {
							"vector": [0, 0, 0]
						},
						"0.125": {
							"vector": [0, 0, 0]
						},
						"0.25": {
							"vector": [0, 0, 0]
						},
						"0.375": {
							"vector": [0, 0, 0]
						},
						"0.5417": {
							"vector": [0, 0, 0]
						},
						"0.6667": {
							"vector": [0, 0, 0]
						},
						"0.7917": {
							"vector": [0, 0, 0]
						}
					}
				}
			}
		}
	},
	"geckolib_format_version": 2
}