{
	"format_version": "1.8.0",
	"animations": {
		"idle": {
			"loop": true,
			"animation_length": 4.5,
			"bones": {
				"Head": {
					"rotation": {
						"0.0": {
							"vector": [5, 0, 0]
						},
						"0.5": {
							"vector": [2.58807, 14.98539, 0.66963]
						},
						"1.0": {
							"vector": [5.40961, -22.40972, -2.06754]
						},
						"1.5": {
							"vector": [2.5, 0, 0]
						},
						"2.0": {
							"vector": [2.5, 0, 0]
						},
						"2.5": {
							"vector": [7.56397, 7.43547, 0.98448]
						},
						"3.0": {
							"vector": [0, 0, 0]
						},
						"3.5": {
							"vector": [7.56397, -7.43547, -0.98448]
						},
						"4.0": {
							"vector": [0, 0, 0]
						},
						"4.5": {
							"vector": [5, 0, 0]
						}
					},
					"position": {
						"0.0": {
							"vector": [0, -1, -2]
						},
						"0.5": {
							"vector": [0, 0, 0]
						},
						"1.0": {
							"vector": [0, -1, -2]
						},
						"1.5": {
							"vector": [0, -1.5, -3]
						},
						"2.0": {
							"vector": [0, 0, 0]
						},
						"2.5": {
							"vector": [0, -0.5, -2]
						},
						"3.0": {
							"vector": [0, 0, 0]
						},
						"3.5": {
							"vector": [0, -0.5, -2]
						},
						"4.0": {
							"vector": [0, 0, 0]
						},
						"4.5": {
							"vector": [0, -1, -2]
						}
					}
				},
				"Body": {
					"rotation": {
						"0.0": {
							"vector": [7.5, 0, 0]
						},
						"0.5": {
							"vector": [0, 0, 0]
						},
						"1.0": {
							"vector": [7.5, 0, 0]
						},
						"1.5": {
							"vector": [7.5, 0, 0]
						},
						"2.0": {
							"vector": [0, 0, 0]
						},
						"2.5": {
							"vector": [5, 0, 0]
						},
						"3.0": {
							"vector": [0, 0, 0]
						},
						"3.5": {
							"vector": [5, 0, 0]
						},
						"4.0": {
							"vector": [0, 0, 0]
						},
						"4.5": {
							"vector": [7.5, 0, 0]
						}
					}
				},
				"chest1": {
					"rotation": {
						"0.0": {
							"vector": [10, 0, 0]
						},
						"0.5": {
							"vector": [0, 0, 0]
						},
						"1.0": {
							"vector": [10, 0, 0]
						},
						"1.5": {
							"vector": [15, 0, 0]
						},
						"2.0": {
							"vector": [0, 0, 0]
						},
						"2.5": {
							"vector": [7.5, 0, 0]
						},
						"3.0": {
							"vector": [0, 0, 0]
						},
						"3.5": {
							"vector": [7.5, 0, 0]
						},
						"4.0": {
							"vector": [0, 0, 0]
						},
						"4.5": {
							"vector": [10, 0, 0]
						}
					}
				},
				"breast": {
					"rotation": {
						"0.0": {
							"vector": [-5, 0, 0]
						},
						"0.5": {
							"vector": [10, 0, 0]
						},
						"1.0": {
							"vector": [-7.5, 0, 0]
						},
						"1.5": {
							"vector": [-7.5, 0, 0]
						},
						"2.0": {
							"vector": [0, 0, 0]
						},
						"2.5": {
							"vector": [-10, 0, 0]
						},
						"3.0": {
							"vector": [0, 0, 0]
						},
						"3.5": {
							"vector": [-10, 0, 0]
						},
						"4.0": {
							"vector": [0, 0, 0]
						},
						"4.5": {
							"vector": [-5, 0, 0]
						}
					},
					"position": {
						"0.0": {
							"vector": [0, 0, 0]
						},
						"1.0": {
							"vector": [0, 0, 0]
						},
						"1.5": {
							"vector": [0, 0, 0]
						},
						"2.0": {
							"vector": [0, 0, 0]
						},
						"4.5": {
							"vector": [0, 0, 0]
						}
					}
				},
				"RArm": {
					"rotation": {
						"0.0": {
							"vector": [-33.53777, -37.85708, 14.7714]
						},
						"0.5": {
							"vector": [-6.73196, -3.83917, 5.00914]
						},
						"1.0": {
							"vector": [-6.76425, -5.62768, 10.17396]
						},
						"1.5": {
							"vector": [-33.53777, -37.85708, 14.7714]
						},
						"2.0": {
							"vector": [-6.73196, -3.83917, 5.00914]
						},
						"2.5": {
							"vector": [-7.29302, -2.61523, 14.94995]
						},
						"3.0": {
							"vector": [-6.73196, -3.83917, 5.00914]
						},
						"3.5": {
							"vector": [-7.29302, -2.61523, 14.94995]
						},
						"4.0": {
							"vector": [-6.73196, -3.83917, 5.00914]
						},
						"4.5": {
							"vector": [-33.53777, -37.85708, 14.7714]
						}
					},
					"position": {
						"0.0": {
							"vector": [0, -1, -2]
						},
						"0.5": {
							"vector": [0, -1, 0]
						},
						"1.0": {
							"vector": [0, -1, -2]
						},
						"1.5": {
							"vector": [0, -1, -3]
						},
						"2.0": {
							"vector": [0, -1, 0]
						},
						"2.5": {
							"vector": [0, -1, -1.5]
						},
						"3.0": {
							"vector": [0, -1, 0]
						},
						"3.5": {
							"vector": [0, -1, -1.5]
						},
						"4.0": {
							"vector": [0, -1, 0]
						},
						"4.5": {
							"vector": [0, -1, -2]
						}
					}
				},
				"Rarm2": {
					"rotation": {
						"0.0": {
							"vector": [-42.5, 0, 0]
						},
						"1.0": {
							"vector": [-15, 0, 0]
						},
						"1.5": {
							"vector": [-42.5, 0, 0]
						},
						"2.5": {
							"vector": [-17.5, 0, 0]
						},
						"3.0": {
							"vector": [-5, 0, 0]
						},
						"3.5": {
							"vector": [-17.5, 0, 0]
						},
						"4.0": {
							"vector": [-5, 0, 0]
						},
						"4.5": {
							"vector": [-42.5, 0, 0]
						}
					}
				},
				"LArm": {
					"rotation": {
						"0.0": {
							"vector": [-0.39362, 13.77769, -11.05801]
						},
						"0.5": {
							"vector": [-0.5453, -3.70166, -8.43423]
						},
						"1.0": {
							"vector": [14.32043, -8.02665, -16.65087]
						},
						"1.5": {
							"vector": [-0.39362, 13.77769, -11.05801]
						},
						"2.0": {
							"vector": [-0.5453, -3.70166, -8.43423]
						},
						"2.5": {
							"vector": [0.10668, -3.74004, -18.45533]
						},
						"3.0": {
							"vector": [-0.86626, -3.64003, -3.42432]
						},
						"3.5": {
							"vector": [0.10668, -3.74004, -18.45533]
						},
						"4.0": {
							"vector": [-0.86626, -3.64003, -3.42432]
						},
						"4.5": {
							"vector": [-0.39362, 13.77769, -11.05801]
						}
					},
					"position": {
						"0.0": {
							"vector": [0, -1, -2]
						},
						"0.5": {
							"vector": [0, -1, 0]
						},
						"1.0": {
							"vector": [0, -1, -2]
						},
						"1.5": {
							"vector": [0, -1, -3]
						},
						"2.0": {
							"vector": [0, -1, 0]
						},
						"2.5": {
							"vector": [0, -1, -1]
						},
						"3.0": {
							"vector": [0, -1, 0]
						},
						"3.5": {
							"vector": [0, -1, -1]
						},
						"4.0": {
							"vector": [0, -1, 0]
						},
						"4.5": {
							"vector": [0, -1, -2]
						}
					}
				},
				"Larm2": {
					"rotation": {
						"0.0": {
							"vector": [-57.5, 0, 0]
						},
						"0.5": {
							"vector": [-15, 0, 0]
						},
						"1.0": {
							"vector": [-57.5, 0, 0]
						},
						"1.5": {
							"vector": [-57.5, 0, 0]
						},
						"2.0": {
							"vector": [-15, 0, 0]
						},
						"3.0": {
							"vector": [-5, 0, 0]
						},
						"4.0": {
							"vector": [-5, 0, 0]
						},
						"4.5": {
							"vector": [-57.5, 0, 0]
						}
					}
				},
				"RLeg": {
					"rotation": {
						"vector": [-2.5, 0, 0]
					}
				},
				"Rleg2": {
					"rotation": {
						"vector": [5, 0, 0]
					}
				},
				"LLeg": {
					"rotation": {
						"vector": [-2.5, 0, 0]
					}
				},
				"Lleg2": {
					"rotation": {
						"vector": [5, 0, 0]
					}
				}
			}
		},
		"walk": {
			"loop": true,
			"animation_length": 1.33333,
			"bones": {
				"Head": {
					"rotation": {
						"0.0": {
							"vector": [0, 0, 2.5]
						},
						"0.3333": {
							"vector": [0, 5, 2.5]
						},
						"0.6667": {
							"vector": [0, 0, 2.5]
						},
						"1.0": {
							"vector": [0, 0, -2.5]
						},
						"1.3333": {
							"vector": [0, 0, 2.5]
						}
					},
					"position": {
						"0.0": {
							"vector": [0, -1, -3]
						},
						"0.3333": {
							"vector": [0, -1, -3]
						},
						"0.6667": {
							"vector": [0, -1, -2]
						},
						"1.0": {
							"vector": [0, -1, -3]
						},
						"1.3333": {
							"vector": [0, -1, -3]
						}
					}
				},
				"Body": {
					"rotation": {
						"0.0": {
							"vector": [7.52832, 4.95712, 0.65426]
						},
						"0.3333": {
							"vector": [7.50706, -2.4786, -0.32652]
						},
						"0.6667": {
							"vector": [7.52832, 4.95712, 0.65426]
						},
						"1.0": {
							"vector": [7.50706, -2.4786, -0.32652]
						},
						"1.3333": {
							"vector": [7.52832, 4.95712, 0.65426]
						}
					}
				},
				"chest1": {
					"rotation": {
						"0.0": {
							"vector": [15.08453, 7.38542, 1.30962]
						},
						"0.3333": {
							"vector": [14.96851, -2.27429, -1.28255]
						},
						"0.6667": {
							"vector": [15.08453, 7.38542, 1.30962]
						},
						"1.0": {
							"vector": [14.96851, -2.27429, -1.28255]
						},
						"1.3333": {
							"vector": [15.08453, 7.38542, 1.30962]
						}
					}
				},
				"breast": {
					"rotation": {
						"0.0": {
							"vector": [0, 0, 0]
						},
						"0.3333": {
							"vector": [-10, 0, 0]
						},
						"0.6667": {
							"vector": [2.46706, 0.00972, 1.08828]
						},
						"1.0": {
							"vector": [-4.98571, -0.01418, 0.00124]
						},
						"1.3333": {
							"vector": [0, 0, 0]
						}
					},
					"position": {
						"0.0": {
							"vector": [0, 0, 0]
						},
						"1.3333": {
							"vector": [0, 0, 0]
						}
					}
				},
				"RArm": {
					"rotation": {
						"0.0": {
							"vector": [-68.95432, -36.72886, 53.5186]
						},
						"0.3333": {
							"vector": [-40.48058, -20.47063, 21.15708]
						},
						"0.6667": {
							"vector": [-31.45432, -36.72886, 53.5186]
						},
						"1.0": {
							"vector": [-47.98058, -20.47063, 21.15708]
						},
						"1.3333": {
							"vector": [-68.95432, -36.72886, 53.5186]
						}
					},
					"position": {
						"0.0": {
							"vector": [-1, -1, -2]
						},
						"0.3333": {
							"vector": [-1, -1, -3]
						},
						"0.6667": {
							"vector": [-1, -1, -1]
						},
						"1.0": {
							"vector": [-1, -1, -4]
						},
						"1.3333": {
							"vector": [-1, -1, -2]
						}
					}
				},
				"Rarm2": {
					"rotation": {
						"0.0": {
							"vector": [-42.5, 0, 0]
						},
						"0.3333": {
							"vector": [-70, 0, 0]
						},
						"0.6667": {
							"vector": [-70.83, 0, 0]
						},
						"1.0": {
							"vector": [-42.5, 0, 0]
						},
						"1.3333": {
							"vector": [-42.5, 0, 0]
						}
					}
				},
				"LArm": {
					"rotation": {
						"0.0": {
							"vector": [-2.89362, 13.77769, -11.05801]
						},
						"0.3333": {
							"vector": [37.12355, -0.69088, -11.27943]
						},
						"0.6667": {
							"vector": [-2.89362, 13.77769, -11.05801]
						},
						"1.0": {
							"vector": [42.12355, -0.69088, -11.27943]
						},
						"1.3333": {
							"vector": [-2.89362, 13.77769, -11.05801]
						}
					},
					"position": {
						"0.0": {
							"vector": [0, -1, -4]
						},
						"0.3333": {
							"vector": [0, -1, -1]
						},
						"0.6667": {
							"vector": [0, -1, -4]
						},
						"1.0": {
							"vector": [0, -1, -1]
						},
						"1.3333": {
							"vector": [0, -1, -4]
						}
					}
				},
				"Larm2": {
					"rotation": {
						"0.0": {
							"vector": [-57.5, 0, 0]
						},
						"1.0": {
							"vector": [-42.5, 0, 0]
						},
						"1.3333": {
							"vector": [-57.5, 0, 0]
						}
					}
				},
				"RLeg": {
					"rotation": {
						"0.0": {
							"vector": [-24.97766, 1.15408, 2.21783]
						},
						"0.3333": {
							"vector": [32.52234, 1.15408, 2.21783]
						},
						"0.6667": {
							"vector": [-17.47766, 1.15408, 2.21783]
						},
						"1.0": {
							"vector": [32.52234, 1.15408, 2.21783]
						},
						"1.3333": {
							"vector": [-24.97766, 1.15408, 2.21783]
						}
					}
				},
				"Rleg2": {
					"rotation": {
						"0.0": {
							"vector": [20, 0, 0]
						},
						"0.3333": {
							"vector": [42.5, 0, 0]
						},
						"0.6667": {
							"vector": [7.5, 0, 0]
						},
						"1.0": {
							"vector": [41.25, 0, 0]
						},
						"1.3333": {
							"vector": [20, 0, 0]
						}
					}
				},
				"LLeg": {
					"rotation": {
						"0.0": {
							"vector": [32.5, 0, 0]
						},
						"0.3333": {
							"vector": [-32.5, 0, 0]
						},
						"0.6667": {
							"vector": [32.5, 0, 0]
						},
						"1.0": {
							"vector": [-32.5, 0, 0]
						},
						"1.3333": {
							"vector": [32.5, 0, 0]
						}
					}
				},
				"Lleg2": {
					"rotation": {
						"0.0": {
							"vector": [25, 0, 0]
						},
						"0.3333": {
							"vector": [37.5, 0, 0]
						},
						"0.6667": {
							"vector": [45.83, 0, 0]
						},
						"1.0": {
							"vector": [22.92, 0, 0]
						},
						"1.3333": {
							"vector": [25, 0, 0]
						}
					}
				}
			}
		},
		"swim": {
			"loop": true,
			"animation_length": 2,
			"bones": {
				"Head": {
					"rotation": {
						"0.0": {
							"vector": [5, 0, 0]
						},
						"0.5": {
							"vector": [17.5, 0, 0]
						},
						"1.0": {
							"vector": [5, 0, 0]
						},
						"1.5": {
							"vector": [17.5, 0, 0]
						},
						"2.0": {
							"vector": [5, 0, 0]
						}
					},
					"position": {
						"0.0": {
							"vector": [0, 0, -1]
						},
						"1.0": {
							"vector": [0, 0, -1]
						},
						"2.0": {
							"vector": [0, 0, -1]
						}
					}
				},
				"chest1": {
					"rotation": {
						"0.0": {
							"vector": [12.5, 0, 0]
						},
						"1.0": {
							"vector": [12.5, 0, 0]
						},
						"2.0": {
							"vector": [12.5, 0, 0]
						}
					}
				},
				"breast": {
					"rotation": {
						"0.0": {
							"vector": [0, 0, 0]
						},
						"0.5": {
							"vector": [-7.5, 0, 0]
						},
						"0.75": {
							"vector": [5, 0, 0]
						},
						"1.0": {
							"vector": [0, 0, 0]
						},
						"1.5": {
							"vector": [-7.5, 0, 0]
						},
						"1.75": {
							"vector": [5, 0, 0]
						},
						"2.0": {
							"vector": [0, 0, 0]
						}
					}
				},
				"RArm": {
					"rotation": {
						"0.0": {
							"vector": [0, 0, 72.5]
						},
						"0.5": {
							"vector": [-70, 0, 72.5]
						},
						"0.75": {
							"vector": [-12.5, 0, 72.5]
						},
						"1.0": {
							"vector": [0, 0, 72.5]
						},
						"1.5": {
							"vector": [-70, 0, 72.5]
						},
						"1.75": {
							"vector": [-12.5, 0, 72.5]
						},
						"2.0": {
							"vector": [0, 0, 72.5]
						}
					},
					"position": {
						"0.0": {
							"vector": [0, -1, -1]
						},
						"1.0": {
							"vector": [0, -1, -1]
						},
						"2.0": {
							"vector": [0, -1, -1]
						}
					}
				},
				"Rarm2": {
					"rotation": {
						"0.0": {
							"vector": [-15, 0, 0]
						},
						"0.5": {
							"vector": [-35, 0, 0]
						},
						"0.75": {
							"vector": [-5, 0, 0]
						},
						"1.0": {
							"vector": [-15, 0, 0]
						},
						"1.5": {
							"vector": [-35, 0, 0]
						},
						"1.75": {
							"vector": [-5, 0, 0]
						},
						"2.0": {
							"vector": [-15, 0, 0]
						}
					}
				},
				"LArm": {
					"rotation": {
						"0.0": {
							"vector": [0, 0, -72.5]
						},
						"0.5": {
							"vector": [-75, 0, -72.5]
						},
						"0.75": {
							"vector": [-5, 0, -72.5]
						},
						"1.0": {
							"vector": [0, 0, -72.5]
						},
						"1.5": {
							"vector": [-75, 0, -72.5]
						},
						"1.75": {
							"vector": [-5, 0, -72.5]
						},
						"2.0": {
							"vector": [0, 0, -72.5]
						}
					},
					"position": {
						"0.0": {
							"vector": [0, -1, -1]
						},
						"1.0": {
							"vector": [0, -1, -1]
						},
						"2.0": {
							"vector": [0, -1, -1]
						}
					}
				},
				"Larm2": {
					"rotation": {
						"0.0": {
							"vector": [-15, 0, 0]
						},
						"0.5": {
							"vector": [-35, 0, 0]
						},
						"0.75": {
							"vector": [0, 0, 0]
						},
						"1.0": {
							"vector": [-15, 0, 0]
						},
						"1.5": {
							"vector": [-35, 0, 0]
						},
						"1.75": {
							"vector": [0, 0, 0]
						},
						"2.0": {
							"vector": [-15, 0, 0]
						}
					}
				},
				"RLeg": {
					"rotation": {
						"0.0": {
							"vector": [9.91615, -1.29876, 7.38733]
						},
						"0.5": {
							"vector": [-25.08385, -1.29876, 7.38733]
						},
						"1.0": {
							"vector": [9.91615, -1.29876, 7.38733]
						},
						"1.5": {
							"vector": [19.91615, -1.29876, 7.38733]
						},
						"2.0": {
							"vector": [9.91615, -1.29876, 7.38733]
						}
					}
				},
				"Rleg2": {
					"rotation": {
						"0.0": {
							"vector": [30, 0, 0]
						},
						"0.5": {
							"vector": [10, 0, 0]
						},
						"1.0": {
							"vector": [30, 0, 0]
						},
						"1.5": {
							"vector": [35, 0, 0]
						},
						"2.0": {
							"vector": [30, 0, 0]
						}
					}
				},
				"LLeg": {
					"rotation": {
						"0.0": {
							"vector": [-2.46207, -0.43399, -9.99067]
						},
						"0.5": {
							"vector": [12.53793, -0.43399, -9.99067]
						},
						"1.0": {
							"vector": [-2.46207, -0.43399, -9.99067]
						},
						"1.5": {
							"vector": [-24.96207, -0.43399, -9.99067]
						},
						"2.0": {
							"vector": [-2.46207, -0.43399, -9.99067]
						}
					}
				},
				"Lleg2": {
					"rotation": {
						"0.0": {
							"vector": [22.5, 0, 0]
						},
						"0.5": {
							"vector": [45, 0, 0]
						},
						"1.0": {
							"vector": [22.5, 0, 0]
						},
						"1.5": {
							"vector": [22.5, 0, 0]
						},
						"2.0": {
							"vector": [22.5, 0, 0]
						}
					}
				}
			}
		},
		"attack": {
			"animation_length": 0.625,
			"bones": {
				"Head": {
					"rotation": {
						"0.0": {
							"vector": [0, 0, 0]
						},
						"0.25": {
							"vector": [5.36938, 1.51439, 3.63746]
						},
						"0.4167": {
							"vector": [12.35712, -5.11703, 1.08521]
						},
						"0.625": {
							"vector": [0, 0, 0]
						}
					},
					"position": {
						"0.0": {
							"vector": [0, 0, 0]
						},
						"0.25": {
							"vector": [0, 0, 0]
						},
						"0.4167": {
							"vector": [0, -1, -2]
						},
						"0.625": {
							"vector": [0, 0, 0]
						}
					}
				},
				"Body": {
					"rotation": {
						"0.0": {
							"vector": [0, 0, 0]
						},
						"0.25": {
							"vector": [-2.5, 0, 0]
						},
						"0.625": {
							"vector": [0, 0, 0]
						}
					},
					"position": {
						"0.0": {
							"vector": [0, 0, 0]
						},
						"0.625": {
							"vector": [0, 0, 0]
						}
					}
				},
				"chest1": {
					"rotation": {
						"0.0": {
							"vector": [0, 0, 0]
						},
						"0.25": {
							"vector": [-4.75568, 14.69057, 2.53516]
						},
						"0.4167": {
							"vector": [20.6469, -14.0761, -5.23619]
						},
						"0.625": {
							"vector": [0, 0, 0]
						}
					},
					"position": {
						"0.0": {
							"vector": [0, 0, 0]
						},
						"0.625": {
							"vector": [0, 0, 0]
						}
					}
				},
				"breast": {
					"rotation": {
						"0.0": {
							"vector": [0, 0, 0]
						},
						"0.25": {
							"vector": [15, 0, 0]
						},
						"0.4167": {
							"vector": [-12.5, 0, 0]
						},
						"0.625": {
							"vector": [0, 0, 0]
						}
					}
				},
				"chest2": {
					"rotation": {
						"0.0": {
							"vector": [0, 0, 0]
						},
						"0.25": {
							"vector": [0, 10, 0]
						},
						"0.4167": {
							"vector": [0, -5, 0]
						},
						"0.625": {
							"vector": [0, 0, 0]
						}
					},
					"position": {
						"0.0": {
							"vector": [0, 0, 0]
						},
						"0.625": {
							"vector": [0, 0, 0]
						}
					}
				},
				"RArm": {
					"rotation": {
						"0.0": {
							"vector": [0, 0, 0]
						},
						"0.25": {
							"vector": [-118.21045, 23.94811, 4.30518]
						},
						"0.4167": {
							"vector": [-30.31187, -9.96685, -32.15791]
						},
						"0.625": {
							"vector": [0, 0, 0]
						}
					},
					"position": {
						"0.0": {
							"vector": [0, 0, 0]
						},
						"0.25": {
							"vector": [0, 0, 2]
						},
						"0.4167": {
							"vector": [0, -1, -3]
						},
						"0.625": {
							"vector": [0, 0, 0]
						}
					}
				},
				"Rarm2": {
					"rotation": {
						"0.0": {
							"vector": [0, 0, 0]
						},
						"0.25": {
							"vector": [-75, 0, 0]
						},
						"0.4167": {
							"vector": [-20, 0, 0]
						},
						"0.625": {
							"vector": [0, 0, 0]
						}
					}
				},
				"LArm": {
					"rotation": {
						"0.0": {
							"vector": [0, 0, 0]
						},
						"0.25": {
							"vector": [-63.75931, 35.98888, -35.33575]
						},
						"0.4167": {
							"vector": [-5.631, -13.54492, -19.61434]
						},
						"0.625": {
							"vector": [0, 0, 0]
						}
					},
					"position": {
						"0.0": {
							"vector": [0, 0, 0]
						},
						"0.25": {
							"vector": [1, -1, -1]
						},
						"0.4167": {
							"vector": [0, -1, 0]
						},
						"0.625": {
							"vector": [0, 0, 0]
						}
					}
				},
				"Larm2": {
					"rotation": {
						"0.0": {
							"vector": [0, 0, 0]
						},
						"0.25": {
							"vector": [-62.5, 0, 0]
						},
						"0.625": {
							"vector": [0, 0, 0]
						}
					},
					"position": {
						"0.0": {
							"vector": [0, 0, 0]
						},
						"0.625": {
							"vector": [0, 0, 0]
						}
					}
				},
				"RLeg": {
					"rotation": {
						"0.0": {
							"vector": [0, 0, 0]
						},
						"0.25": {
							"vector": [-7.5, 7.5, 0]
						},
						"0.4167": {
							"vector": [-11.66667, 4.16667, 0]
						},
						"0.625": {
							"vector": [0, 0, 0]
						}
					},
					"position": {
						"0.0": {
							"vector": [0, 0, 0]
						},
						"0.25": {
							"vector": [0, 0, 1]
						},
						"0.625": {
							"vector": [0, 0, 0]
						}
					}
				},
				"Rleg2": {
					"rotation": {
						"0.0": {
							"vector": [0, 0, 0]
						},
						"0.25": {
							"vector": [7.5, 0, 0]
						},
						"0.4167": {
							"vector": [12.5, 0, 0]
						},
						"0.625": {
							"vector": [0, 0, 0]
						}
					}
				},
				"LLeg": {
					"rotation": {
						"0.0": {
							"vector": [0, 0, 0]
						},
						"0.25": {
							"vector": [13.603, -17.93186, -10.98222]
						},
						"0.4167": {
							"vector": [-7.44278, -9.96214, -6.10123]
						},
						"0.625": {
							"vector": [0, 0, 0]
						}
					},
					"position": {
						"0.0": {
							"vector": [0, 0, 0]
						},
						"0.625": {
							"vector": [0, 0, 0]
						}
					}
				},
				"Lleg2": {
					"rotation": {
						"0.0": {
							"vector": [0, 0, 0]
						},
						"0.25": {
							"vector": [17.5, 0, 0]
						},
						"0.4167": {
							"vector": [12.5, 0, 0]
						},
						"0.625": {
							"vector": [0, 0, 0]
						}
					}
				}
			}
		}
	},
	"geckolib_format_version": 2
}